[
    {
        "date": "Mon Jul 27 2020",
        "time": "12:09:26",
        "title": "Body Burn Challenge",
        "price": "free"
    },
    {
        "date": "Tue Jul 21 2020",
        "time": "05:09:26",
        "title": "Breathing Exercise",
        "price": "free"
    },
    {
        "date": "Mon Jul 13 2020",
        "time": "02:09:26",
        "title": "thursday turndown with coach",
        "price": "free"
    },
    {
        "date": "Fri Jul 17 2020",
        "time": "23:09:26",
        "title": "thursday turndown with coach",
        "price": "free"
    }
]